<?xml version='1.0' encoding='utf-8'?>
<program language="IPPcode24"><instruction order="1" opcode="DEFVAR"><arg1 type="var">GF@a</arg1></instruction><instruction order="2" opcode="READ"><arg1 type="var">GF@a</arg1><arg2 type="var">int</arg2></instruction><instruction order="3" opcode="DEFVAR"><arg1 type="var">GF@b</arg1></instruction><instruction order="4" opcode="READ"><arg1 type="var">GF@b</arg1><arg2 type="var">int</arg2></instruction><instruction order="5" opcode="DEFVAR"><arg1 type="var">GF@c</arg1></instruction><instruction order="6" opcode="ADD"><arg1 type="var">GF@c</arg1><arg2 type="var">GF@a</arg2><arg3 type="var">GF@b</arg3></instruction><instruction order="7" opcode="DEFVAR"><arg1 type="var">GF@__LOOP_1_cond</arg1></instruction><instruction order="8" opcode="GT"><arg1 type="var">GF@__LOOP_1_cond</arg1><arg2 type="var">GF@c</arg2><arg3 type="var">int@0</arg3></instruction><instruction order="9" opcode="LABEL"><arg1 type="var">__LOOP_1_start</arg1></instruction></program>